[{"title":"银、剑、石：拉丁美洲的三重烙印 (点击查看图片)","author":"玛丽・阿拉纳","downloadUrl":"https://url89.ctfile.com/f/31084289-1357003672-fa8a61?p=8866"},{"title":"佩恩先生 (点击查看图片)","author":"罗贝托・波拉尼奥","downloadUrl":"https://url89.ctfile.com/f/31084289-1356985156-46b0f6?p=8866"},{"title":"布宜诺斯艾利斯传 (点击查看图片)","author":"詹姆斯・加德纳","downloadUrl":"https://url89.ctfile.com/f/31084289-1357051075-377d9d?p=8866"},{"title":"花与恶心 (点击查看图片)","author":"卡洛斯・德鲁蒙德・德・安德拉德","downloadUrl":"https://url89.ctfile.com/f/31084289-1357043881-7197ca?p=8866"},{"title":"十个女人 (点击查看图片)","author":"马塞拉・塞拉诺","downloadUrl":"https://url89.ctfile.com/f/31084289-1357037614-efe484?p=8866"},{"title":"掉队的拉美 (点击查看图片)","author":"塞巴斯蒂安・爱德华兹","downloadUrl":"https://url89.ctfile.com/f/31084289-1357035082-3c2a50?p=8866"},{"title":"没有人给他写信的上校 (点击查看图片)","author":"加西亚・马尔克斯","downloadUrl":"https://url89.ctfile.com/f/31084289-1357034659-dfacc3?p=8866"},{"title":"安第斯山脉的生与死 (点击查看图片)","author":"金・麦夸里","downloadUrl":"https://url89.ctfile.com/f/31084289-1357032457-1c064e?p=8866"},{"title":"印加帝国的末日 (点击查看图片)","author":"金・麦夸里","downloadUrl":"https://url89.ctfile.com/f/31084289-1357032436-e2b271?p=8866"},{"title":"风景画家的片段人生 (点击查看图片)","author":"塞萨尔・艾拉","downloadUrl":"https://url89.ctfile.com/f/31084289-1357032295-900cb5?p=8866"},{"title":"黑羊 (点击查看图片)","author":"奥古斯托・蒙特罗索","downloadUrl":"https://url89.ctfile.com/f/31084289-1357028038-89760c?p=8866"},{"title":"斗牛士之名 (点击查看图片)","author":"路易斯・塞普尔维达","downloadUrl":"https://url89.ctfile.com/f/31084289-1357027405-82e241?p=8866"},{"title":"天谴 (点击查看图片)","author":"塞尔希奥・拉米雷斯","downloadUrl":"https://url89.ctfile.com/f/31084289-1357024861-a5cc92?p=8866"},{"title":"族长的秋天 (点击查看图片)","author":"加西亚・马尔克斯","downloadUrl":"https://url89.ctfile.com/f/31084289-1357022356-073aeb?p=8866"},{"title":"克罗诺皮奥与法玛的故事 (点击查看图片)","author":"胡利奥・科塔萨尔","downloadUrl":"https://url89.ctfile.com/f/31084289-1357017775-747156?p=8866"}]