[{"title":"超现实 (点击查看图片)","author":"杰里米・拜伦森","downloadUrl":"https://url89.ctfile.com/f/31084289-1375513297-854053?p=8866"},{"title":"破译人类的明天 (点击查看图片)","author":"迈克尔・李","downloadUrl":"https://url89.ctfile.com/f/31084289-1357000984-c69a46?p=8866"},{"title":"隐藏的行为 (点击查看图片)","author":"托马斯・科洛波洛斯","downloadUrl":"https://url89.ctfile.com/f/31084289-1357053679-c73b9c?p=8866"},{"title":"治愈未来 (点击查看图片)","author":"安德鲁・基恩","downloadUrl":"https://url89.ctfile.com/f/31084289-1357052638-8a1ece?p=8866"},{"title":"人机共生 (点击查看图片)","author":"托马斯・达文波特/茱莉娅・柯尔比","downloadUrl":"https://url89.ctfile.com/f/31084289-1357052242-ae31e9?p=8866"},{"title":"欢迎来到敌托邦 (点击查看图片)","author":"戈登・范・格尔德","downloadUrl":"https://url89.ctfile.com/f/31084289-1357049440-137c79?p=8866"},{"title":"智能城市 (点击查看图片)","author":"卡洛・拉蒂","downloadUrl":"https://url89.ctfile.com/f/31084289-1357047313-0afc1e?p=8866"},{"title":"人工智能会抢哪些工作 (点击查看图片)","author":"理查德・萨斯坎德/丹尼尔・萨斯坎德","downloadUrl":"https://url89.ctfile.com/f/31084289-1357046014-d3f3a4?p=8866"},{"title":"AI的25种可能 (点击查看图片)","author":"约翰・布罗克曼","downloadUrl":"https://url89.ctfile.com/f/31084289-1357045990-ebb4e9?p=8866"},{"title":"科技失控 (点击查看图片)","author":"温德尔・瓦拉赫","downloadUrl":"https://url89.ctfile.com/f/31084289-1357045468-5452cb?p=8866"},{"title":"超级思维 (点击查看图片)","author":"托马斯·W·马隆","downloadUrl":"https://url89.ctfile.com/f/31084289-1357045216-ccaf96?p=8866"},{"title":"未来版图 (点击查看图片)","author":"麻省理工科技评论","downloadUrl":"https://url89.ctfile.com/f/31084289-1357040737-6c7837?p=8866"},{"title":"空荡荡的地球 (点击查看图片)","author":"达雷尔・布里克/约翰・伊比特森","downloadUrl":"https://url89.ctfile.com/f/31084289-1357039507-2d7877?p=8866"},{"title":"18个未来进行时 (点击查看图片)","author":"吉姆・阿尔- 哈里里","downloadUrl":"https://url89.ctfile.com/f/31084289-1357033387-b60047?p=8866"},{"title":"第三次浪潮 (点击查看图片)","author":"阿尔文・托夫勒","downloadUrl":"https://url89.ctfile.com/f/31084289-1357032949-77397f?p=8866"},{"title":"最后一个人类 (点击查看图片)","author":"马克・奥康奈尔","downloadUrl":"https://url89.ctfile.com/f/31084289-1357027636-2d1cd6?p=8866"},{"title":"未来50年 (点击查看图片)","author":"约翰・布罗克曼","downloadUrl":"https://url89.ctfile.com/f/31084289-1357027123-c3d4eb?p=8866"},{"title":"你一定爱读的极简未来史 (点击查看图片)","author":"克里斯托弗・巴纳特","downloadUrl":"https://url89.ctfile.com/f/31084289-1357025617-432176?p=8866"},{"title":"四维人类 (点击查看图片)","author":"劳伦斯・斯科特","downloadUrl":"https://url89.ctfile.com/f/31084289-1357024183-b1d497?p=8866"},{"title":"虚拟现实：万象的新开端 (点击查看图片)","author":"杰伦・拉尼尔","downloadUrl":"https://url89.ctfile.com/f/31084289-1357023481-c4b2a4?p=8866"},{"title":"不会被机器替代的人 (点击查看图片)","author":"杰夫・科尔文","downloadUrl":"https://url89.ctfile.com/f/31084289-1357023115-85b483?p=8866"},{"title":"超级智能 (点击查看图片)","author":"尼克・波斯特洛姆","downloadUrl":"https://url89.ctfile.com/f/31084289-1357023076-a138b3?p=8866"},{"title":"人类的明天 (点击查看图片)","author":"席里尔・迪翁","downloadUrl":"https://url89.ctfile.com/f/31084289-1357022440-689a22?p=8866"},{"title":"机器70年 (点击查看图片)","author":"徐曦","downloadUrl":"https://url89.ctfile.com/f/31084289-1357022332-319d8b?p=8866"},{"title":"AI·未来 (点击查看图片)","author":"李开复","downloadUrl":"https://url89.ctfile.com/f/31084289-1357022242-192485?p=8866"},{"title":"资源革命 (点击查看图片)","author":"斯蒂芬・赫克等","downloadUrl":"https://url89.ctfile.com/f/31084289-1357021423-f18c7d?p=8866"},{"title":"微粒社会 (点击查看图片)","author":"克里斯托夫・库克里克","downloadUrl":"https://url89.ctfile.com/f/31084289-1357019575-e3c742?p=8866"},{"title":"掌控未来系列（套装共6册） (点击查看图片)","author":"伊藤穰一等","downloadUrl":"https://url89.ctfile.com/f/31084289-1357018420-d99af9?p=8866"},{"title":"虚拟人 (点击查看图片)","author":"玛蒂娜・罗斯布拉特","downloadUrl":"https://url89.ctfile.com/f/31084289-1357018252-b38b81?p=8866"},{"title":"超越人类 (点击查看图片)","author":"伊芙・赫洛尔德","downloadUrl":"https://url89.ctfile.com/f/31084289-1357017697-b3e68f?p=8866"},{"title":"奇点临近 (点击查看图片)","author":"雷・库兹韦尔","downloadUrl":"https://url89.ctfile.com/f/31084289-1357017070-174382?p=8866"},{"title":"终极复制 (点击查看图片)","author":"李智勇","downloadUrl":"https://url89.ctfile.com/f/31084289-1357015513-c9f8c7?p=8866"},{"title":"复杂：信息时代的连接、机会与布局 (点击查看图片)","author":"罗家德","downloadUrl":"https://url89.ctfile.com/f/31084289-1357014691-5f5ec3?p=8866"},{"title":"The 100-Year Life (点击查看图片)","author":"Lynda Gratton / Andrew Scott","downloadUrl":"https://url89.ctfile.com/f/31084289-1357013686-e885a9?p=8866"},{"title":"人类2.0：在硅谷探索科技未来 (点击查看图片)","author":"皮埃罗・斯加鲁菲","downloadUrl":"https://url89.ctfile.com/f/31084289-1357011589-1e110c?p=8866"},{"title":"人工智能时代 (点击查看图片)","author":"杰瑞・卡普兰","downloadUrl":"https://url89.ctfile.com/f/31084289-1357009093-321621?p=8866"},{"title":"人工智能 (点击查看图片)","author":"李开复/王咏刚","downloadUrl":"https://url89.ctfile.com/f/31084289-1357008751-19b821?p=8866"},{"title":"2052：未来四十年的中国与世界 (点击查看图片)","author":"乔根・兰德斯","downloadUrl":"https://url89.ctfile.com/f/31084289-1357008022-6de1f8?p=8866"},{"title":"必然 (点击查看图片)","author":"凯文・凯利","downloadUrl":"https://url89.ctfile.com/f/31084289-1357007995-a3825d?p=8866"},{"title":"新一轮产业革命 (点击查看图片)","author":"亚力克・罗斯","downloadUrl":"https://url89.ctfile.com/f/31084289-1357007671-2f2880?p=8866"}]