[{"title":"生命的起源 (点击查看图片)","author":"刘大可","downloadUrl":"https://url89.ctfile.com/f/31084289-1375497466-2034fd?p=8866"},{"title":"我们为什么长这样 (点击查看图片)","author":"爱丽丝・罗伯茨","downloadUrl":"https://url89.ctfile.com/f/31084289-1375498861-27862a?p=8866"},{"title":"在病毒中生存 (点击查看图片)","author":"苗德岁","downloadUrl":"https://url89.ctfile.com/f/31084289-1375500622-0a9910?p=8866"},{"title":"5分钟生物课 (点击查看图片)","author":"冯智","downloadUrl":"https://url89.ctfile.com/f/31084289-1375511134-5ad126?p=8866"},{"title":"生命是什么：活细胞的物理观 (点击查看图片)","author":"埃尔温・薛定谔","downloadUrl":"https://url89.ctfile.com/f/31084289-1357003762-6a6963?p=8866"},{"title":"生命是什么：40亿年生命史诗的开端 (点击查看图片)","author":"埃迪・普罗斯","downloadUrl":"https://url89.ctfile.com/f/31084289-1357003546-7d4c71?p=8866"},{"title":"致命接触（第二版） (点击查看图片)","author":"大卫・奎曼","downloadUrl":"https://url89.ctfile.com/f/31084289-1356995455-e3dd7a?p=8866"},{"title":"基因与命运 (点击查看图片)","author":"斯蒂芬·J.海涅","downloadUrl":"https://url89.ctfile.com/f/31084289-1356985726-a126a7?p=8866"},{"title":"生命之源 (点击查看图片)","author":"尼克・連恩","downloadUrl":"https://url89.ctfile.com/f/31084289-1356985378-57f1a6?p=8866"},{"title":"极端生存 (点击查看图片)","author":"史蒂芬・帕鲁比/安东尼・帕鲁比","downloadUrl":"https://url89.ctfile.com/f/31084289-1357045501-c5f1f7?p=8866"},{"title":"我包罗万象 (点击查看图片)","author":"埃德・扬","downloadUrl":"https://url89.ctfile.com/f/31084289-1357043266-561836?p=8866"},{"title":"创世记 (点击查看图片)","author":"爱德华・威尔逊","downloadUrl":"https://url89.ctfile.com/f/31084289-1357038829-745a6a?p=8866"},{"title":"反本能生存学 (点击查看图片)","author":"李・戈德曼","downloadUrl":"https://url89.ctfile.com/f/31084289-1357038757-646e30?p=8866"},{"title":"科学元典套装（五） (点击查看图片)","author":"惠更斯等","downloadUrl":"https://url89.ctfile.com/f/31084289-1357035748-b4937c?p=8866"},{"title":"人类的算法 (点击查看图片)","author":"罗宾・邓巴","downloadUrl":"https://url89.ctfile.com/f/31084289-1357033690-f7e5dd?p=8866"},{"title":"驯化 (点击查看图片)","author":"艾丽丝・罗伯茨","downloadUrl":"https://url89.ctfile.com/f/31084289-1357031020-9dc347?p=8866"},{"title":"动物城邦系列（共四册） (点击查看图片)","author":"伯特・霍尔多布勒等","downloadUrl":"https://url89.ctfile.com/f/31084289-1357030435-d80ab8?p=8866"},{"title":"龙：一种未明的动物（增订本） (点击查看图片)","author":"马小星","downloadUrl":"https://url89.ctfile.com/f/31084289-1357028452-c59106?p=8866"},{"title":"美的进化 (点击查看图片)","author":"理查德·O.普鲁姆","downloadUrl":"https://url89.ctfile.com/f/31084289-1357027783-fd1f03?p=8866"},{"title":"生命密码 (点击查看图片)","author":"尹烨","downloadUrl":"https://url89.ctfile.com/f/31084289-1357025089-016748?p=8866"},{"title":"缤纷的生命 (点击查看图片)","author":"爱德华・威尔逊","downloadUrl":"https://url89.ctfile.com/f/31084289-1357024873-81e121?p=8866"},{"title":"刘易斯·托马斯作品（共5册） (点击查看图片)","author":"刘易斯・托马斯","downloadUrl":"https://url89.ctfile.com/f/31084289-1357024816-c54ec4?p=8866"},{"title":"基因、大脑和人类潜能 (点击查看图片)","author":"肯・理查森","downloadUrl":"https://url89.ctfile.com/f/31084289-1357024378-df4a92?p=8866"},{"title":"重新设计生命 (点击查看图片)","author":"约翰・帕林顿","downloadUrl":"https://url89.ctfile.com/f/31084289-1357023517-a7a1c5?p=8866"},{"title":"盲眼钟表匠 (点击查看图片)","author":"理查德・道金斯","downloadUrl":"https://url89.ctfile.com/f/31084289-1357023208-874cd3?p=8866"},{"title":"未完成的进化 (点击查看图片)","author":"凯文・拉兰德","downloadUrl":"https://url89.ctfile.com/f/31084289-1357023028-0a6723?p=8866"},{"title":"人类存在的意义 (点击查看图片)","author":"爱德华・威尔逊","downloadUrl":"https://url89.ctfile.com/f/31084289-1357021663-2150bf?p=8866"},{"title":"生命的未来：从双螺旋到合成生命 (点击查看图片)","author":"克雷格・文特尔","downloadUrl":"https://url89.ctfile.com/f/31084289-1357020724-9f0385?p=8866"},{"title":"百科通识全系列大套装（共49本） (点击查看图片)","author":"安德鲁・巴兰坦等","downloadUrl":"https://url89.ctfile.com/f/31084289-1357020376-81a38d?p=8866"},{"title":"上帝的手术刀 (点击查看图片)","author":"王立铭","downloadUrl":"https://url89.ctfile.com/f/31084289-1357018852-dc5d45?p=8866"},{"title":"基因传 (点击查看图片)","author":"悉达多・穆克吉","downloadUrl":"https://url89.ctfile.com/f/31084289-1357016893-23588d?p=8866"},{"title":"地球上最伟大的表演 (点击查看图片)","author":"理查德・毛姆道金斯","downloadUrl":"https://url89.ctfile.com/f/31084289-1357014634-2565d2?p=8866"},{"title":"与机器赛跑 (点击查看图片)","author":"埃里克・布林约尔松","downloadUrl":"https://url89.ctfile.com/f/31084289-1357012012-9217f7?p=8866"},{"title":"生命是什么 (点击查看图片)","author":"王立铭","downloadUrl":"https://url89.ctfile.com/f/31084289-1357009738-c0bfb9?p=8866"},{"title":"致命接触：全球大型传染病探秘之旅 (点击查看图片)","author":"大卫·奎曼","downloadUrl":"https://url89.ctfile.com/f/31084289-1357007101-3f4fe7?p=8866"}]