[{"title":"去规模化 (点击查看图片)","author":"赫曼特・塔内佳/凯文・梅尼","downloadUrl":"https://url89.ctfile.com/f/31084289-1356994687-e7d6a6?p=8866"},{"title":"隐藏的行为 (点击查看图片)","author":"托马斯・科洛波洛斯","downloadUrl":"https://url89.ctfile.com/f/31084289-1357053679-c73b9c?p=8866"},{"title":"人机共生 (点击查看图片)","author":"托马斯・达文波特/茱莉娅・柯尔比","downloadUrl":"https://url89.ctfile.com/f/31084289-1357052242-ae31e9?p=8866"},{"title":"第三次浪潮 (点击查看图片)","author":"阿尔文・托夫勒","downloadUrl":"https://url89.ctfile.com/f/31084289-1357032949-77397f?p=8866"},{"title":"小宣言 (点击查看图片)","author":"马格努斯・林奎斯特","downloadUrl":"https://url89.ctfile.com/f/31084289-1357027162-16e6c5?p=8866"},{"title":"趋势戒律 (点击查看图片)","author":"柯弗","downloadUrl":"https://url89.ctfile.com/f/31084289-1357026925-f60e50?p=8866"},{"title":"变量 (点击查看图片)","author":"何帆","downloadUrl":"https://url89.ctfile.com/f/31084289-1357026250-f993f8?p=8866"},{"title":"虚拟现实：万象的新开端 (点击查看图片)","author":"杰伦・拉尼尔","downloadUrl":"https://url89.ctfile.com/f/31084289-1357023481-c4b2a4?p=8866"},{"title":"富足：改变人类未来的4大力量 (点击查看图片)","author":"彼得・戴曼迪斯","downloadUrl":"https://url89.ctfile.com/f/31084289-1357015900-a0dfb0?p=8866"},{"title":"趋势红利 (点击查看图片)","author":"刘润","downloadUrl":"https://url89.ctfile.com/f/31084289-1357015312-024ddb?p=8866"},{"title":"必然 (点击查看图片)","author":"凯文・凯利","downloadUrl":"https://url89.ctfile.com/f/31084289-1357007995-a3825d?p=8866"}]