[{"title":"毒枪手：慕尼黑的秘密间谍 (点击查看图片)","author":"沙希利・浦洛基","downloadUrl":"https://url89.ctfile.com/f/31084289-1375498735-7e0be3?p=8866"},{"title":"暗黑之门 (点击查看图片)","author":"理查德・阿尔德里奇/罗里・科马克","downloadUrl":"https://url89.ctfile.com/f/31084289-1356999205-192c10?p=8866"},{"title":"海明威与骗子工厂 (点击查看图片)","author":"丹・西蒙斯","downloadUrl":"https://url89.ctfile.com/f/31084289-1357053163-da42f2?p=8866"},{"title":"代号D机关Ⅲ (点击查看图片)","author":"柳广司","downloadUrl":"https://url89.ctfile.com/f/31084289-1357034080-736199?p=8866"},{"title":"代号D机关Ⅰ (点击查看图片)","author":"柳广司","downloadUrl":"https://url89.ctfile.com/f/31084289-1357033729-239911?p=8866"},{"title":"代号D机关Ⅱ (点击查看图片)","author":"柳广司","downloadUrl":"https://url89.ctfile.com/f/31084289-1357033720-1dd32f?p=8866"},{"title":"无处可藏 (点击查看图片)","author":"格伦・格林沃尔德","downloadUrl":"https://url89.ctfile.com/f/31084289-1357033462-b25888?p=8866"},{"title":"美国情报界 (点击查看图片)","author":"杰弗瑞・理查尔森","downloadUrl":"https://url89.ctfile.com/f/31084289-1357023136-5c184c?p=8866"},{"title":"尔虞我诈：中国古代四千年谍海风云（全2册） (点击查看图片)","author":"赵英","downloadUrl":"https://url89.ctfile.com/f/31084289-1357008742-adf1c5?p=8866"},{"title":"间谍王：戴笠与中国特工 (点击查看图片)","author":"魏斐德","downloadUrl":"https://url89.ctfile.com/f/31084289-1357008571-4000d9?p=8866"},{"title":"CIA美国中央情报局全传 (点击查看图片)","author":"亚诺","downloadUrl":"https://url89.ctfile.com/f/31084289-1357007401-df2110?p=8866"},{"title":"国家阴谋5：火焰王子 (点击查看图片)","author":"丹尼尔・席尔瓦","downloadUrl":"https://url89.ctfile.com/f/31084289-1357006324-542463?p=8866"},{"title":"7本书带你走进间谍圈（全七册） (点击查看图片)","author":"弗·福赛斯","downloadUrl":"https://url89.ctfile.com/f/31084289-1357005466-1df1de?p=8866"},{"title":"风起陇西 (点击查看图片)","author":"马伯庸","downloadUrl":"https://url89.ctfile.com/f/31084289-1357005358-f7a76a?p=8866"}]